gd_fup/__init__.py
gd_fup/progress_bar.py
gd_fup/service.py
gd_fup/updater.py
google_drive_file_updater-0.0.5.data/scripts/gdfup.py
google_drive_file_updater-0.0.5.dist-info/METADATA
google_drive_file_updater-0.0.5.dist-info/WHEEL
google_drive_file_updater-0.0.5.dist-info/top_level.txt
google_drive_file_updater-0.0.5.dist-info/RECORD
