Metadata-Version: 2.1
Name: google-drive-file-updater
Version: 0.0.5
Summary: Google Drive file updater
Home-page: UNKNOWN
Author: Daniel Riffert
Author-email: riffert.daniel@gmail.com
License: UNKNOWN
Keywords: file,update,path,backup,google drive
Platform: UNKNOWN
Requires-Dist: colorama
Requires-Dist: pywin32
Requires-Dist: google-api-python-client
Requires-Dist: google-auth-httplib2
Requires-Dist: google-auth-oauthlib
